_2048/ClearSans-Bold.ttf
_2048/ClearSans.ttf
_2048/__init__.py
_2048/__main__.py
_2048/game.py
_2048/lock.py
_2048/main.py
_2048/manager.py
_2048/utils.py
2048-0.3.3.dist-info/LICENSE
2048-0.3.3.dist-info/METADATA
2048-0.3.3.dist-info/WHEEL
2048-0.3.3.dist-info/entry_points.txt
2048-0.3.3.dist-info/top_level.txt
2048-0.3.3.dist-info/RECORD
