Metadata-Version: 2.1
Name: 2048
Version: 0.3.3
Summary: Quantum's version of the 2048 game, with multi-instance support,restored from an old high school project.
Home-page: https://github.com/quantum5/2048
Author: quantum
Author-email: quantum2048@gmail.com
License: UNKNOWN
Keywords: 2048 pygame
Platform: UNKNOWN
Classifier: Development Status :: 4 - Beta
Classifier: Environment :: Win32 (MS Windows)
Classifier: Environment :: X11 Applications
Classifier: Intended Audience :: End Users/Desktop
Classifier: License :: OSI Approved :: GNU General Public License v3 (GPLv3)
Classifier: Operating System :: Microsoft :: Windows
Classifier: Operating System :: POSIX :: Linux
Classifier: Programming Language :: Python
Classifier: Programming Language :: Python :: 2
Classifier: Programming Language :: Python :: 2.7
Classifier: Programming Language :: Python :: 3
Classifier: Programming Language :: Python :: 3.4
Classifier: Programming Language :: Python :: 3.5
Classifier: Programming Language :: Python :: 3.6
Classifier: Topic :: Games/Entertainment
Requires-Dist: appdirs
Requires-Dist: pygame
